ipynb_scrubber/__init__.py
ipynb_scrubber/__main__.py
ipynb_scrubber/__version__.py
ipynb_scrubber/cli.py
ipynb_scrubber/exceptions.py
ipynb_scrubber/processor.py
ipynb_scrubber/py.typed
ipynb_scrubber-0.2.0.dist-info/METADATA
ipynb_scrubber-0.2.0.dist-info/WHEEL
ipynb_scrubber-0.2.0.dist-info/entry_points.txt
ipynb_scrubber-0.2.0.dist-info/licenses/LICENSE
ipynb_scrubber-0.2.0.dist-info/RECORD
