Metadata-Version: 2.4
Name: ipynb-scrubber
Version: 0.2.0
Summary: Generate exercise versions of Jupyter notebooks
Project-URL: Repository, https://github.com/jkeifer/ipynb-scrubber
Author-email: Jarrett Keifer <jkeifer0@gmail.com>
License: Apache License 2.0
License-File: LICENSE
Requires-Python: >=3.12
